egain_api_python/__init__.py
egain_api_python/_version.py
egain_api_python/aiservices.py
egain_api_python/answers.py
egain_api_python/articlelists.py
egain_api_python/basesdk.py
egain_api_python/connectorssearchevents.py
egain_api_python/content.py
egain_api_python/escalation.py
egain_api_python/export.py
egain_api_python/federatedsearchevent.py
egain_api_python/general.py
egain_api_python/guidedhelp.py
egain_api_python/httpclient.py
egain_api_python/import_.py
egain_api_python/populararticles.py
egain_api_python/portal_article.py
egain_api_python/portal_attachment.py
egain_api_python/portal_bookmark.py
egain_api_python/portal_sdk.py
egain_api_python/portal_suggestion.py
egain_api_python/portal_topic.py
egain_api_python/portal_userdetails.py
egain_api_python/portal_userprofile.py
egain_api_python/py.typed
egain_api_python/retrieve.py
egain_api_python/sdk.py
egain_api_python/sdkconfiguration.py
egain_api_python/search.py
egain_api_python/usermilestones.py
egain_api_python/_hooks/__init__.py
egain_api_python/_hooks/registration.py
egain_api_python/_hooks/sdkhooks.py
egain_api_python/_hooks/types.py
egain_api_python/errors/__init__.py
egain_api_python/errors/egaindefaulterror.py
egain_api_python/errors/egainerror.py
egain_api_python/errors/no_response_error.py
egain_api_python/errors/responsevalidationerror.py
egain_api_python/errors/schemas_wserrorcommon.py
egain_api_python/errors/wserrorcommon.py
egain_api_python/models/__init__.py
egain_api_python/models/acceptghsolutionop.py
egain_api_python/models/acceptlanguage.py
egain_api_python/models/accessibleportal.py
egain_api_python/models/action.py
egain_api_python/models/actionsearch.py
egain_api_python/models/addasreferenceop.py
egain_api_python/models/addbookmarkop.py
egain_api_python/models/additionalsnippets.py
egain_api_python/models/addtoreplyop.py
egain_api_python/models/aisearchop.py
egain_api_python/models/aisearchresponse.py
egain_api_python/models/aitopicbreadcrumb.py
egain_api_python-0.1.10.dist-info/licenses/LICENSE
egain_api_python-0.1.10.dist-info/METADATA
egain_api_python-0.1.10.dist-info/WHEEL
egain_api_python-0.1.10.dist-info/top_level.txt
egain_api_python-0.1.10.dist-info/RECORD
